setup.py
CommonFileAPI/CommonAPI.py
CommonFileAPI/SQLiteAPI.py
CommonFileAPI/__init__.py
CommonFileAPIForPython.egg-info/PKG-INFO
CommonFileAPIForPython.egg-info/SOURCES.txt
CommonFileAPIForPython.egg-info/dependency_links.txt
CommonFileAPIForPython.egg-info/top_level.txt