Metadata-Version: 1.1
Name: CommonFileAPIForPython
Version: 0.0.1
Summary: Functions to make file handling even easier!
Home-page: http://packages.python.org/CommonFileAPIForPython
Author: Alasdair Morrison
Author-email: amorri40@gmail.com
License: BSD
Keywords: common file database sqlite
Platform: UNKNOWN
Classifier: Development Status :: 3 - Alpha
Classifier: Topic :: Utilities
Classifier: License :: OSI Approved :: BSD License
